SEPTeX/LaTeX.py
SEPTeX/TeXBase.py
SEPTeX/TeXUtils.py
SEPTeX/TikZ.py
SEPTeX/TikZBase.py
SEPTeX/TikZGraph.py
SEPTeX/__init__.py
SEPTeX/_test/__init__.py
SEPTeX/_test/demo.py
SEPTeX/_test/test_LaTeX.py
SEPTeX/_test/test_TeXBase.py
SEPTeX/_test/test_TikZBase.py
SEPTeX-0.4.0.dist-info/METADATA
SEPTeX-0.4.0.dist-info/WHEEL
SEPTeX-0.4.0.dist-info/top_level.txt
SEPTeX-0.4.0.dist-info/RECORD
