Metadata-Version: 2.1
Name: SEPTeX
Version: 0.4.0
Summary: SEPTeX is a wrapper library for generating TeX/TikZ code through Python.
Home-page: https://github.com/MarcelSimader/SEPTeX/
Author: Marcel Simader
Author-email: marcel0simader@gmail.com
License: UNKNOWN
Project-URL: Documentation, https://marcelsimader.github.io/SEPTeX/
Project-URL: Source, https://github.com/MarcelSimader/SEPTeX/
Platform: UNKNOWN
Classifier: Programming Language :: Python :: 3.9
Classifier: Development Status :: 3 - Alpha
Classifier: License :: Free for non-commercial use
Classifier: Operating System :: Unix
Classifier: Environment :: Console
Requires-Python: >=3.8
